data_ingest_filters/__init__.py
data_ingest_filters/data_ingest_filter.py
data_ingest_filters/data_ingest_filter_wrapper.py
data_ingest_filters/utils.py
data_ingest_filters-1.25.0.dev0.dist-info/METADATA
data_ingest_filters-1.25.0.dev0.dist-info/WHEEL
data_ingest_filters-1.25.0.dev0.dist-info/top_level.txt
data_ingest_filters-1.25.0.dev0.dist-info/RECORD
