Metadata-Version: 2.4
Name: data_ingest_filters
Version: 1.25.0.dev0
Summary: Python based data ingest filters
Author: Akridata Inc
Author-email: support@akridata.com
Classifier: Programming Language :: Python :: 3
Classifier: Operating System :: OS Independent
Requires-Dist: akriml>=0.2.0
Requires-Dist: numpy>=1.19.2
Requires-Dist: pandas==1.5.1
Requires-Dist: pyakri_de_utils==1.25.0.dev0
Requires-Dist: pyarrow==14.0.1
Dynamic: author
Dynamic: author-email
Dynamic: classifier
Dynamic: requires-dist
Dynamic: summary
